illini_snake/__init__.py
illini_snake/__main__.py
illini_snake/base.py
illini_snake/food.py
illini_snake/game.py
illini_snake/screen.py
illini_snake/settings.json
illini_snake/snake.py
illini_snake/square.py
illini_snake/utils.py
illini_snake/static/Illinois.png
illini_snake/static/nom nom nom.wav
illini_snake/static/opponent_logos/Indiana.svg
illini_snake/static/opponent_logos/Iowa.png
illini_snake/static/opponent_logos/Maryland.png
illini_snake/static/opponent_logos/Michigan State.png
illini_snake/static/opponent_logos/Michigan.png
illini_snake/static/opponent_logos/Minnesota.png
illini_snake/static/opponent_logos/Nebraska.png
illini_snake/static/opponent_logos/Northwestern.png
illini_snake/static/opponent_logos/Ohio State.png
illini_snake/static/opponent_logos/Penn State.png
illini_snake/static/opponent_logos/Purdue.png
illini_snake/static/opponent_logos/Rutgers.png
illini_snake/static/opponent_logos/Wisconsin.png
illini_snake-0.2.0.dist-info/LICENSE
illini_snake-0.2.0.dist-info/METADATA
illini_snake-0.2.0.dist-info/WHEEL
illini_snake-0.2.0.dist-info/top_level.txt
illini_snake-0.2.0.dist-info/RECORD
