Metadata-Version: 2.1
Name: illini_snake
Version: 0.2.0
Summary: An illini-themed snake game
Home-page: https://pypi.org/project/illini-snake
Author: James Kabbes
Author-email: james.kabbes@gmail.com
Project-URL: GitHub, https://github.com/jameskabbes/illini-snake
Project-URL: Documentation, https://jameskabbes.github.io/illini-snake
Classifier: Programming Language :: Python :: 3
Classifier: License :: OSI Approved :: MIT License
Classifier: Operating System :: OS Independent
Requires-Python: >=3.7
License-File: LICENSE
